microrabbit/__init__.py
microrabbit/abc.py
microrabbit/logger.py
microrabbit/app/__init__.py
microrabbit/app/rabbit_client.py
microrabbit/app/utils.py
microrabbit/types/__init__.py
microrabbit/types/enums.py
microrabbit/types/options.py
microrabbit-0.5.2.dist-info/LICENSE
microrabbit-0.5.2.dist-info/METADATA
microrabbit-0.5.2.dist-info/WHEEL
microrabbit-0.5.2.dist-info/top_level.txt
microrabbit-0.5.2.dist-info/RECORD
