Metadata-Version: 2.1
Name: microrabbit
Version: 0.5.2
Summary: A simple RabbitMQ client for Python
Author: TonnoBelloSnello
Maintainer: TonnoBelloSnello, TelegramXPlus
Requires-Python: >=3.8
License-File: LICENSE
Requires-Dist: aio-pika ==9.4.2
Requires-Dist: pydantic ==2.9.2
